<?xml version="1.0" encoding="UTF-8"?>
<qes:espresso xsi:schemaLocation="http://www.quantum-espresso.org/ns/qes/qes-1.0 http://www.quantum-espresso.org/ns/qes/qes_030920.xsd" Units="Hartree atomic units" xmlns:xsi="http://www.w3.org/2001/XMLSchema-instance" xmlns:qes="http://www.quantum-espresso.org/ns/qes/qes-1.0">
  <!--All quantities are in Hartree atomic units unless otherwise specified-->
  <general_info>
    <xml_format NAME="QEXSD" VERSION="20.04.20">QEXSD_20.04.20</xml_format>
    <creator NAME="PWSCF" VERSION="6.7MaX">XML file generated by PWSCF</creator>
    <created DATE="15Nov2021" TIME="15:42:21">This run was terminated on:  15:42:21  15 Nov 2021</created>
    <job></job>
  </general_info>
  <parallel_info>
    <nprocs>10</nprocs>
    <nthreads>1</nthreads>
    <ntasks>1</ntasks>
    <nbgrp>1</nbgrp>
    <npool>1</npool>
    <ndiag>10</ndiag>
  </parallel_info>
  <output>
    <convergence_info>
      <scf_conv>
        <convergence_achieved>true</convergence_achieved>
        <n_scf_steps>32</n_scf_steps>
        <scf_error>2.114227947794766e-9</scf_error>
      </scf_conv>
    </convergence_info>
    <algorithmic_info>
      <real_space_q>false</real_space_q>
      <real_space_beta>false</real_space_beta>
      <uspp>true</uspp>
      <paw>true</paw>
    </algorithmic_info>
    <atomic_species ntyp="2" pseudo_dir="../Pseudo/">
      <species name="Mo">
        <mass>9.593999999999999e1</mass>
        <pseudo_file>Mo.pbe-spn-kjpaw_psl.0.2.UPF</pseudo_file>
      </species>
      <species name="S">
        <mass>3.206500000000000e1</mass>
        <pseudo_file>S.pbe-n-kjpaw_psl.0.1.UPF</pseudo_file>
      </species>
    </atomic_species>
    <atomic_structure nat="3" alat="5.983000000000e0">
      <atomic_positions>
        <atom name="Mo" index="1">0.000000000000000e0 1.824675955080000e-2 0.000000000000000e0</atom>
        <atom name="S" index="2">0.000000000000000e0 3.500189823913499e0 2.961068910608100e0</atom>
        <atom name="S" index="3">0.000000000000000e0 3.500189823913499e0 -2.961068910608100e0</atom>
      </atomic_positions>
      <cell>
        <a1>6.031269108929999e0 0.000000000000000e0 0.000000000000000e0</a1>
        <a2>-3.015634554465000e0 5.222586911523000e0 0.000000000000000e0</a2>
        <a3>0.000000000000000e0 0.000000000000000e0 2.133111411333900e1</a3>
      </cell>
    </atomic_structure>
    <symmetries>
      <nsym>4</nsym>
      <nrot>8</nrot>
      <space_group>0</space_group>
      <symmetry>
        <info name="identity">crystal_symmetry</info>
        <rotation rank="2" dims="3 3" order="F">
          1.000000000000000e0 0.000000000000000e0 0.000000000000000e0
          0.000000000000000e0 1.000000000000000e0 0.000000000000000e0
          0.000000000000000e0 0.000000000000000e0 1.000000000000000e0
          </rotation>
        <fractional_translation>0.000000000000000e0 0.000000000000000e0 0.000000000000000e0</fractional_translation>
        <equivalent_atoms nat="3" size="3">
          1 2 3
          </equivalent_atoms>
      </symmetry>
      <symmetry>
        <info name="180 deg rotation - cart. axis [0,1,0]">crystal_symmetry</info>
        <rotation rank="2" dims="3 3" order="F">
          -1.000000000000000e0 1.000000000000000e0 0.000000000000000e0
          0.000000000000000e0 1.000000000000000e0 0.000000000000000e0
          0.000000000000000e0 0.000000000000000e0 -1.000000000000000e0
          </rotation>
        <fractional_translation>0.000000000000000e0 0.000000000000000e0 0.000000000000000e0</fractional_translation>
        <equivalent_atoms nat="3" size="3">
          1 3 2
          </equivalent_atoms>
      </symmetry>
      <symmetry>
        <info name="inv. 180 deg rotation - cart. axis [0,0,1]">crystal_symmetry</info>
        <rotation rank="2" dims="3 3" order="F">
          1.000000000000000e0 0.000000000000000e0 0.000000000000000e0
          0.000000000000000e0 1.000000000000000e0 0.000000000000000e0
          0.000000000000000e0 0.000000000000000e0 -1.000000000000000e0
          </rotation>
        <fractional_translation>0.000000000000000e0 0.000000000000000e0 0.000000000000000e0</fractional_translation>
        <equivalent_atoms nat="3" size="3">
          1 3 2
          </equivalent_atoms>
      </symmetry>
      <symmetry>
        <info name="inv. 180 deg rotation - cart. axis [1,0,0]">crystal_symmetry</info>
        <rotation rank="2" dims="3 3" order="F">
          -1.000000000000000e0 1.000000000000000e0 0.000000000000000e0
          0.000000000000000e0 1.000000000000000e0 0.000000000000000e0
          0.000000000000000e0 0.000000000000000e0 1.000000000000000e0
          </rotation>
        <fractional_translation>0.000000000000000e0 0.000000000000000e0 0.000000000000000e0</fractional_translation>
        <equivalent_atoms nat="3" size="3">
          1 2 3
          </equivalent_atoms>
      </symmetry>
      <symmetry>
        <info name="inversion">lattice_symmetry</info>
        <rotation rank="2" dims="3 3" order="F">
          -1.000000000000000e0 0.000000000000000e0 0.000000000000000e0
          0.000000000000000e0 -1.000000000000000e0 0.000000000000000e0
          0.000000000000000e0 0.000000000000000e0 -1.000000000000000e0
          </rotation>
      </symmetry>
      <symmetry>
        <info name="180 deg rotation - cart. axis [0,0,1]">lattice_symmetry</info>
        <rotation rank="2" dims="3 3" order="F">
          -1.000000000000000e0 0.000000000000000e0 0.000000000000000e0
          0.000000000000000e0 -1.000000000000000e0 0.000000000000000e0
          0.000000000000000e0 0.000000000000000e0 1.000000000000000e0
          </rotation>
      </symmetry>
      <symmetry>
        <info name="inv. 180 deg rotation - cart. axis [0,1,0]">lattice_symmetry</info>
        <rotation rank="2" dims="3 3" order="F">
          1.000000000000000e0 -1.000000000000000e0 0.000000000000000e0
          0.000000000000000e0 -1.000000000000000e0 0.000000000000000e0
          0.000000000000000e0 0.000000000000000e0 1.000000000000000e0
          </rotation>
      </symmetry>
      <symmetry>
        <info name="180 deg rotation - cart. axis [1,0,0]">lattice_symmetry</info>
        <rotation rank="2" dims="3 3" order="F">
          1.000000000000000e0 -1.000000000000000e0 0.000000000000000e0
          0.000000000000000e0 -1.000000000000000e0 0.000000000000000e0
          0.000000000000000e0 0.000000000000000e0 -1.000000000000000e0
          </rotation>
      </symmetry>
    </symmetries>
    <basis_set>
      <gamma_only>false</gamma_only>
      <ecutwfc>2.500000000000000e1</ecutwfc>
      <ecutrho>2.500000000000000e2</ecutrho>
      <fft_grid nr1="45" nr2="45" nr3="160"></fft_grid>
      <fft_smooth nr1="27" nr2="27" nr3="100"></fft_smooth>
      <fft_box nr1="45" nr2="45" nr3="160"></fft_box>
      <ngm>126991</ngm>
      <ngms>32155</ngms>
      <npwx>4040</npwx>
      <reciprocal_lattice>
        <b1>9.919968570365178e-1 5.728004245175166e-1 0.000000000000000e0</b1>
        <b2>0.000000000000000e0 1.145600849035033e0 0.000000000000000e0</b2>
        <b3>0.000000000000000e0 0.000000000000000e0 2.804823024343884e-1</b3>
      </reciprocal_lattice>
    </basis_set>
    <dft>
      <functional>PBE</functional>
    </dft>
    <magnetization>
      <lsda>false</lsda>
      <noncolin>false</noncolin>
      <spinorbit>false</spinorbit>
      <total>0.000000000000000e0</total>
      <absolute>0.000000000000000e0</absolute>
    </magnetization>
    <total_energy>
      <etot>-2.483451224068177e2</etot>
      <eband>-1.280604728775769e1</eband>
      <ehart>1.076165136125065e2</ehart>
      <vtxc>-1.719883579805237e1</vtxc>
      <etxc>-2.127615703498839e1</etxc>
      <ewald>2.772637987883597e1</ewald>
    </total_energy>
    <band_structure>
      <lsda>false</lsda>
      <noncolin>false</noncolin>
      <spinorbit>false</spinorbit>
      <nbnd>13</nbnd>
      <nelec>2.600000000000000e1</nelec>
      <num_of_atomic_wfc>21</num_of_atomic_wfc>
      <wf_collected>true</wf_collected>
      <fermi_energy>1.032185721847141e-1</fermi_energy>
      <highestOccupiedLevel>1.032185721847141e-1</highestOccupiedLevel>
      <starting_k_points>
        <monkhorst_pack nk1="18" nk2="18" nk3="1" k1="0" k2="0" k3="0">Monkhorst-Pack</monkhorst_pack>
      </starting_k_points>
      <nks>91</nks>
      <occupations_kind>fixed</occupations_kind>
      <ks_energies>
        <k_point weight="6.172839506173e-3">0.000000000000000e0 0.000000000000000e0 0.000000000000000e0</k_point>
        <npw>4009</npw>
        <eigenvalues size="13">
          -2.135024710080375e0 -1.184050523945665e0 -1.176785813043131e0 -1.176778298102513e0 -4.127843518833196e-1
          -3.657615404205394e-1 -1.016294176695280e-1 8.364285032233873e-3 8.406372147989604e-3 3.907890198294812e-2
          4.894819592659754e-2 4.900160020344471e-2 1.029541047131304e-1
          </eigenvalues>
        <occupations size="13">
          1.000000000000000e0 1.000000000000000e0 1.000000000000000e0 1.000000000000000e0 1.000000000000000e0
          1.000000000000000e0 1.000000000000000e0 1.000000000000000e0 1.000000000000000e0 1.000000000000000e0
          1.000000000000000e0 1.000000000000000e0 1.000000000000000e0
          </occupations>
      </ks_energies>
      <ks_energies>
        <k_point weight="1.234567901235e-2">0.000000000000000e0 6.364449161305740e-2 0.000000000000000e0</k_point>
        <npw>3997</npw>
        <eigenvalues size="13">
          -2.134984759063063e0 -1.183970169289034e0 -1.177186478938627e0 -1.176878743631717e0 -4.111239029503442e-1
          -3.650641683870895e-1 -9.969091972467352e-2 4.556051518854431e-3 1.012039163830188e-2 2.875585459119287e-2
          4.620161448541383e-2 5.682386447937789e-2 1.021812956546325e-1
          </eigenvalues>
        <occupations size="13">
          1.000000000000000e0 1.000000000000000e0 1.000000000000000e0 1.000000000000000e0 1.000000000000000e0
          1.000000000000000e0 1.000000000000000e0 1.000000000000000e0 1.000000000000000e0 1.000000000000000e0
          1.000000000000000e0 1.000000000000000e0 1.000000000000000e0
          </occupations>
      </ks_energies>
      <ks_energies>
        <k_point weight="1.234567901235e-2">0.000000000000000e0 1.272889832261148e-1 0.000000000000000e0</k_point>
        <npw>4005</npw>
        <eigenvalues size="13">
          -2.134869796878295e0 -1.183739705875477e0 -1.178361319000979e0 -1.177146703976396e0 -4.062570180707430e-1
          -3.630202176611206e-1 -9.422750515201090e-2 -5.713878936113431e-3 1.367512494422421e-2 1.522540345125740e-2
          3.887411791478541e-2 6.352409065442838e-2 9.918917541525101e-2
          </eigenvalues>
        <occupations size="13">
          1.000000000000000e0 1.000000000000000e0 1.000000000000000e0 1.000000000000000e0 1.000000000000000e0
          1.000000000000000e0 1.000000000000000e0 1.000000000000000e0 1.000000000000000e0 1.000000000000000e0
          1.000000000000000e0 1.000000000000000e0 1.000000000000000e0
          </occupations>
      </ks_energies>
      <ks_energies>
        <k_point weight="1.234567901235e-2">0.000000000000000e0 1.909334748391722e-1 0.000000000000000e0</k_point>
        <npw>4006</npw>
        <eigenvalues size="13">
          -2.134693494101286e0 -1.183384749480591e0 -1.180149603925823e0 -1.177555914665604e0 -3.985286400886381e-1
          -3.597783050846657e-1 -8.652572131379211e-2 -1.926903054611322e-2 -2.177949192952050e-3 2.317963107643329e-2
          2.894209458781912e-2 6.383896441502539e-2 9.255556104628649e-2
          </eigenvalues>
        <occupations size="13">
          1.000000000000000e0 1.000000000000000e0 1.000000000000000e0 1.000000000000000e0 1.000000000000000e0
          1.000000000000000e0 1.000000000000000e0 1.000000000000000e0 1.000000000000000e0 1.000000000000000e0
          1.000000000000000e0 1.000000000000000e0 1.000000000000000e0
          </occupations>
      </ks_energies>
      <ks_energies>
        <k_point weight="1.234567901235e-2">0.000000000000000e0 2.545779664522296e-1 0.000000000000000e0</k_point>
        <npw>3990</npw>
        <eigenvalues size="13">
          -2.134476928350429e0 -1.182947951801949e0 -1.182323377626232e0 -1.178055818261520e0 -3.885254434605356e-1
          -3.555994679882932e-1 -7.973041070290028e-2 -3.187968823197491e-2 -1.828844233178119e-2 1.829416611447200e-2
          3.311691902555874e-2 5.849202399314219e-2 8.241124995929876e-2
          </eigenvalues>
        <occupations size="13">
          1.000000000000000e0 1.000000000000000e0 1.000000000000000e0 1.000000000000000e0 1.000000000000000e0
          1.000000000000000e0 1.000000000000000e0 1.000000000000000e0 1.000000000000000e0 1.000000000000000e0
          1.000000000000000e0 1.000000000000000e0 1.000000000000000e0
          </occupations>
      </ks_energies>
      <ks_energies>
        <k_point weight="1.234567901235e-2">0.000000000000000e0 3.182224580652870e-1 0.000000000000000e0</k_point>
        <npw>4016</npw>
        <eigenvalues size="13">
          -2.134246264999930e0 -1.184616911893187e0 -1.182483391200923e0 -1.178588377731013e0 -3.771051272843741e-1
          -3.508727669776146e-1 -7.956350020121167e-2 -3.848647035698988e-2 -3.412434446688512e-2 8.293219154044838e-3
          4.379789187517588e-2 5.084124084999411e-2 7.252488313489379e-2
          </eigenvalues>
        <occupations size="13">
          1.000000000000000e0 1.000000000000000e0 1.000000000000000e0 1.000000000000000e0 1.000000000000000e0
          1.000000000000000e0 1.000000000000000e0 1.000000000000000e0 1.000000000000000e0 1.000000000000000e0
          1.000000000000000e0 1.000000000000000e0 1.000000000000000e0
          </occupations>
      </ks_energies>
      <ks_energies>
        <k_point weight="1.234567901235e-2">0.000000000000000e0 3.818669496783444e-1 0.000000000000000e0</k_point>
        <npw>4010</npw>
        <eigenvalues size="13">
          -2.134029117185114e0 -1.186749799134177e0 -1.182045948087822e0 -1.179085934906690e0 -3.654454956019060e-1
          -3.461240565988413e-1 -8.730062371221546e-2 -4.868901197825279e-2 -3.968232181409750e-2 -1.703450903893286e-4
          4.378607858002551e-2 5.373855829815906e-2 6.818626403428039e-2
          </eigenvalues>
        <occupations size="13">
          1.000000000000000e0 1.000000000000000e0 1.000000000000000e0 1.000000000000000e0 1.000000000000000e0
          1.000000000000000e0 1.000000000000000e0 1.000000000000000e0 1.000000000000000e0 1.000000000000000e0
          1.000000000000000e0 1.000000000000000e0 1.000000000000000e0
          </occupations>
      </ks_energies>
      <ks_energies>
        <k_point weight="1.234567901235e-2">0.000000000000000e0 4.455114412914018e-1 0.000000000000000e0</k_point>
        <npw>4032</npw>
        <eigenvalues size="13">
          -2.133851967361612e0 -1.188476432897793e0 -1.181688541956839e0 -1.179491879548737e0 -3.550781029208449e-1
          -3.419947608289200e-1 -9.699589017988060e-2 -6.059599446020543e-2 -4.140144170655744e-2 -6.539921641200690e-3
          3.862502917712805e-2 6.154907586106988e-2 7.114887780564700e-2
          </eigenvalues>
        <occupations size="13">
          1.000000000000000e0 1.000000000000000e0 1.000000000000000e0 1.000000000000000e0 1.000000000000000e0
          1.000000000000000e0 1.000000000000000e0 1.000000000000000e0 1.000000000000000e0 1.000000000000000e0
          1.000000000000000e0 1.000000000000000e0 1.000000000000000e0
          </occupations>
      </ks_energies>
      <ks_energies>
        <k_point weight="1.234567901235e-2">0.000000000000000e0 5.091559329044592e-1 0.000000000000000e0</k_point>
        <npw>4040</npw>
        <eigenvalues size="13">
          -2.133736218781949e0 -1.189596408160102e0 -1.181455224357171e0 -1.179755359059683e0 -3.477788900437701e-1
          -3.391555994705531e-1 -1.043152116318100e-1 -6.843744444538967e-2 -4.405222037558540e-2 -1.047986211261857e-2
          3.560817889399427e-2 6.637870169541779e-2 7.718432776470989e-2
          </eigenvalues>
        <occupations size="13">
          1.000000000000000e0 1.000000000000000e0 1.000000000000000e0 1.000000000000000e0 1.000000000000000e0
          1.000000000000000e0 1.000000000000000e0 1.000000000000000e0 1.000000000000000e0 1.000000000000000e0
          1.000000000000000e0 1.000000000000000e0 1.000000000000000e0
          </occupations>
      </ks_energies>
      <ks_energies>
        <k_point weight="6.172839506173e-3">0.000000000000000e0 -5.728004245175166e-1 0.000000000000000e0</k_point>
        <npw>4034</npw>
        <eigenvalues size="13">
          -2.133695979118275e0 -1.189983473920658e0 -1.181373791314750e0 -1.179846537269900e0 -3.451264804186123e-1
          -3.381401623753258e-1 -1.070168366110751e-1 -7.117806909186024e-2 -4.528618792493721e-2 -1.181218272694723e-2
          3.462787768978675e-2 6.798760558858836e-2 8.012251003233612e-2
          </eigenvalues>
        <occupations size="13">
          1.000000000000000e0 1.000000000000000e0 1.000000000000000e0 1.000000000000000e0 1.000000000000000e0
          1.000000000000000e0 1.000000000000000e0 1.000000000000000e0 1.000000000000000e0 1.000000000000000e0
          1.000000000000000e0 1.000000000000000e0 1.000000000000000e0
          </occupations>
      </ks_energies>
      <ks_energies>
        <k_point weight="2.469135802469e-2">5.511093650202876e-2 3.182224580652870e-2 0.000000000000000e0</k_point>
        <npw>3999</npw>
        <eigenvalues size="13">
          -2.134984787286488e0 -1.183970221556162e0 -1.177192257691894e0 -1.176873003570203e0 -4.111242154702246e-1
          -3.650646301744343e-1 -9.969122369285362e-2 4.526444330562033e-3 1.015172232748505e-2 2.874017324344037e-2
          4.624227401319602e-2 5.679995451827692e-2 1.021798117813998e-1
          </eigenvalues>
        <occupations size="13">
          1.000000000000000e0 1.000000000000000e0 1.000000000000000e0 1.000000000000000e0 1.000000000000000e0
          1.000000000000000e0 1.000000000000000e0 1.000000000000000e0 1.000000000000000e0 1.000000000000000e0
          1.000000000000000e0 1.000000000000000e0 1.000000000000000e0
          </occupations>
      </ks_energies>
      <ks_energies>
        <k_point weight="2.469135802469e-2">5.511093650202876e-2 9.546673741958609e-2 0.000000000000000e0</k_point>
        <npw>3993</npw>
        <eigenvalues size="13">
          -2.134907318163487e0 -1.183814613409629e0 -1.177971243564235e0 -1.177065566824721e0 -4.078601962635072e-1
          -3.636935473600656e-1 -9.597991277582047e-2 -2.465312583126364e-3 1.351685392730865e-2 1.814738431430191e-2
          4.023441149296886e-2 6.300174870205039e-2 1.002992163185873e-1
          </eigenvalues>
        <occupations size="13">
          1.000000000000000e0 1.000000000000000e0 1.000000000000000e0 1.000000000000000e0 1.000000000000000e0
          1.000000000000000e0 1.000000000000000e0 1.000000000000000e0 1.000000000000000e0 1.000000000000000e0
          1.000000000000000e0 1.000000000000000e0 1.000000000000000e0
          </occupations>
      </ks_energies>
      <ks_energies>
        <k_point weight="2.469135802469e-2">5.511093650202876e-2 1.591112290326435e-1 0.000000000000000e0</k_point>
        <npw>4000</npw>
        <eigenvalues size="13">
          -2.134761695127773e0 -1.183521687285812e0 -1.179426095813258e0 -1.177431282504044e0 -4.015596569015317e-1
          -3.610472333647365e-1 -8.930492148708144e-2 -1.421856044140663e-2 4.594420577547047e-3 1.984885583699418e-2
          2.963107957623301e-2 6.686871994184896e-2 9.545725774538401e-2
          </eigenvalues>
        <occupations size="13">
          1.000000000000000e0 1.000000000000000e0 1.000000000000000e0 1.000000000000000e0 1.000000000000000e0
          1.000000000000000e0 1.000000000000000e0 1.000000000000000e0 1.000000000000000e0 1.000000000000000e0
          1.000000000000000e0 1.000000000000000e0 1.000000000000000e0
          </occupations>
      </ks_energies>
      <ks_energies>
        <k_point weight="2.469135802469e-2">5.511093650202876e-2 2.227557206457009e-1 0.000000000000000e0</k_point>
        <npw>3991</npw>
        <eigenvalues size="13">
          -2.134565243158879e0 -1.183125975214717e0 -1.181370176863910e0 -1.177922329539032e0 -3.926836160018012e-1
          -3.573257370263360e-1 -8.170246010459616e-2 -2.713454375714714e-2 -1.023400069023159e-2 1.780414869918827e-2
          2.827545331576532e-2 6.498279966182010e-2 8.690650903759135e-2
          </eigenvalues>
        <occupations size="13">
          1.000000000000000e0 1.000000000000000e0 1.000000000000000e0 1.000000000000000e0 1.000000000000000e0
          1.000000000000000e0 1.000000000000000e0 1.000000000000000e0 1.000000000000000e0 1.000000000000000e0
          1.000000000000000e0 1.000000000000000e0 1.000000000000000e0
          </occupations>
      </ks_energies>
      <ks_energies>
        <k_point weight="2.469135802469e-2">5.511093650202876e-2 2.864002122587583e-1 0.000000000000000e0</k_point>
        <npw>4003</npw>
        <eigenvalues size="13">
          -2.134341628932010e0 -1.183563103639958e0 -1.182675605523727e0 -1.178479626861667e0 -3.819461698812795e-1
          -3.528481947491268e-1 -7.776469188133296e-2 -3.637038072962842e-2 -2.602091077055623e-2 7.296250889629183e-3
          3.730501830969945e-2 5.850659351140479e-2 7.689218262141883e-2
          </eigenvalues>
        <occupations size="13">
          1.000000000000000e0 1.000000000000000e0 1.000000000000000e0 1.000000000000000e0 1.000000000000000e0
          1.000000000000000e0 1.000000000000000e0 1.000000000000000e0 1.000000000000000e0 1.000000000000000e0
          1.000000000000000e0 1.000000000000000e0 1.000000000000000e0
          </occupations>
      </ks_energies>
      <ks_energies>
        <k_point weight="2.469135802469e-2">5.511093650202876e-2 3.500447038718157e-1 0.000000000000000e0</k_point>
        <npw>4007</npw>
        <eigenvalues size="13">
          -2.134117678393330e0 -1.185734877449458e0 -1.182224118365925e0 -1.179035492160665e0 -3.703541311910778e-1
          -3.480673030522355e-1 -8.213972786970608e-2 -4.174640570849336e-2 -3.878840225684356e-2 -8.231761252574719e-4
          4.482196427142200e-2 5.045519586330371e-2 7.102251042677231e-2
          </eigenvalues>
        <occupations size="13">
          1.000000000000000e0 1.000000000000000e0 1.000000000000000e0 1.000000000000000e0 1.000000000000000e0
          1.000000000000000e0 1.000000000000000e0 1.000000000000000e0 1.000000000000000e0 1.000000000000000e0
          1.000000000000000e0 1.000000000000000e0 1.000000000000000e0
          </occupations>
      </ks_energies>
      <ks_energies>
        <k_point weight="2.469135802469e-2">5.511093650202876e-2 4.136891954848730e-1 0.000000000000000e0</k_point>
        <npw>4016</npw>
        <eigenvalues size="13">
          -2.133920505035096e0 -1.187628600435506e0 -1.181826810618432e0 -1.179522768365095e0 -3.592537940224752e-1
          -3.435685187177225e-1 -9.126592158828085e-2 -5.569670120128518e-2 -3.953925409553449e-2 -6.547503424178098e-3
          4.319560316509399e-2 5.015130105098868e-2 7.283913497302064e-2
          </eigenvalues>
        <occupations size="13">
          1.000000000000000e0 1.000000000000000e0 1.000000000000000e0 1.000000000000000e0 1.000000000000000e0
          1.000000000000000e0 1.000000000000000e0 1.000000000000000e0 1.000000000000000e0 1.000000000000000e0
          1.000000000000000e0 1.000000000000000e0 1.000000000000000e0
          </occupations>
      </ks_energies>
      <ks_energies>
        <k_point weight="2.469135802469e-2">5.511093650202876e-2 4.773336870979305e-1 0.000000000000000e0</k_point>
        <npw>4024</npw>
        <eigenvalues size="13">
          -2.133774009395171e0 -1.189025169493440e0 -1.181531224286700e0 -1.179883188879994e0 -3.503097711562231e-1
          -3.400212381064450e-1 -9.974880741747718e-2 -6.614081129509780e-2 -4.206610829828297e-2 -1.016391460307649e-2
          3.796370901285879e-2 5.481698144676798e-2 7.876962864826389e-2
          </eigenvalues>
        <occupations size="13">
          1.000000000000000e0 1.000000000000000e0 1.000000000000000e0 1.000000000000000e0 1.000000000000000e0
          1.000000000000000e0 1.000000000000000e0 1.000000000000000e0 1.000000000000000e0 1.000000000000000e0
          1.000000000000000e0 1.000000000000000e0 1.000000000000000e0
          </occupations>
      </ks_energies>
      <ks_energies>
        <k_point weight="2.469135802469e-2">5.511093650202876e-2 5.409781787109878e-1 0.000000000000000e0</k_point>
        <npw>4027</npw>
        <eigenvalues size="13">
          -2.133696004794021e0 -1.189764886653191e0 -1.181373839892288e0 -1.180074433112391e0 -3.452482777053871e-1
          -3.380519020474403e-1 -1.047000760257827e-1 -7.173349730030666e-2 -4.437504455525315e-2 -1.191175074176448e-2
          3.526824959688747e-2 5.774979965648740e-2 8.368532203525678e-2
          </eigenvalues>
        <occupations size="13">
          1.000000000000000e0 1.000000000000000e0 1.000000000000000e0 1.000000000000000e0 1.000000000000000e0
          1.000000000000000e0 1.000000000000000e0 1.000000000000000e0 1.000000000000000e0 1.000000000000000e0
          1.000000000000000e0 1.000000000000000e0 1.000000000000000e0
          </occupations>
      </ks_energies>
      <ks_energies>
        <k_point weight="2.469135802469e-2">1.102218730040575e-1 6.364449161305740e-2 0.000000000000000e0</k_point>
        <npw>4007</npw>
        <eigenvalues size="13">
          -2.134869890566335e0 -1.183739957987016e0 -1.178366582384533e0 -1.177140760589322e0 -4.062582287390109e-1
          -3.630220645162077e-1 -9.422843386199869e-2 -5.738596481427873e-3 1.365423856269380e-2 1.525601514295753e-2
          3.891649477519287e-2 6.350748542129727e-2 9.918308836779021e-2
          </eigenvalues>
        <occupations size="13">
          1.000000000000000e0 1.000000000000000e0 1.000000000000000e0 1.000000000000000e0 1.000000000000000e0
          1.000000000000000e0 1.000000000000000e0 1.000000000000000e0 1.000000000000000e0 1.000000000000000e0
          1.000000000000000e0 1.000000000000000e0 1.000000000000000e0
          </occupations>
      </ks_energies>
      <ks_energies>
        <k_point weight="2.469135802469e-2">1.102218730040575e-1 1.272889832261148e-1 0.000000000000000e0</k_point>
        <npw>4000</npw>
        <eigenvalues size="13">
          -2.134761760276824e0 -1.183521772382575e0 -1.179428469585672e0 -1.177428326749515e0 -4.015605424725900e-1
          -3.610486407834104e-1 -8.930545500801651e-2 -1.422927860486624e-2 4.581496793297498e-3 1.986331597082319e-2
          2.965326706403342e-2 6.686399002361209e-2 9.545235232114671e-2
          </eigenvalues>
        <occupations size="13">
          1.000000000000000e0 1.000000000000000e0 1.000000000000000e0 1.000000000000000e0 1.000000000000000e0
          1.000000000000000e0 1.000000000000000e0 1.000000000000000e0 1.000000000000000e0 1.000000000000000e0
          1.000000000000000e0 1.000000000000000e0 1.000000000000000e0
          </occupations>
      </ks_energies>
      <ks_energies>
        <k_point weight="2.469135802469e-2">1.102218730040575e-1 1.909334748391722e-1 0.000000000000000e0</k_point>
        <npw>4003</npw>
        <eigenvalues size="13">
          -2.134595993435735e0 -1.183188535153182e0 -1.180995363715311e0 -1.177919807158475e0 -3.941048996540704e-1
          -3.579144700432999e-1 -8.247357920794435e-2 -2.512680412993535e-2 -5.609306296153392e-3 1.446164221789843e-2
          2.624715338079438e-2 6.926375780326079e-2 8.856536364927960e-2
          </eigenvalues>
        <occupations size="13">
          1.000000000000000e0 1.000000000000000e0 1.000000000000000e0 1.000000000000000e0 1.000000000000000e0
          1.000000000000000e0 1.000000000000000e0 1.000000000000000e0 1.000000000000000e0 1.000000000000000e0
          1.000000000000000e0 1.000000000000000e0 1.000000000000000e0
          </occupations>
      </ks_energies>
      <ks_energies>
        <k_point weight="2.469135802469e-2">1.102218730040575e-1 2.545779664522296e-1 0.000000000000000e0</k_point>
        <npw>4007</npw>
        <eigenvalues size="13">
          -2.134392429351174e0 -1.182881312839605e0 -1.182778292291811e0 -1.178544109135568e0 -3.844670575419805e-1
          -3.538663236429632e-1 -7.690889933420245e-2 -3.434804577066869e-2 -1.808713258935932e-2 4.372341522363596e-4
          3.243530444341827e-2 6.689233880583767e-2 7.981187503173403e-2
          </eigenvalues>
        <occupations size="13">
          1.000000000000000e0 1.000000000000000e0 1.000000000000000e0 1.000000000000000e0 1.000000000000000e0
          1.000000000000000e0 1.000000000000000e0 1.000000000000000e0 1.000000000000000e0 1.000000000000000e0
          1.000000000000000e0 1.000000000000000e0 1.000000000000000e0
          </occupations>
      </ks_energies>
      <ks_energies>
        <k_point weight="2.469135802469e-2">1.102218730040575e-1 3.182224580652870e-1 0.000000000000000e0</k_point>
        <npw>4006</npw>
        <eigenvalues size="13">
          -2.134175513576104e0 -1.184861007902468e0 -1.182341003195994e0 -1.179216695122345e0 -3.734912004277464e-1
          -3.492751354449537e-1 -7.770459985694305e-2 -3.743496939186834e-2 -3.434406665553152e-2 -7.611149625523851e-3
          3.553587589348190e-2 6.014900285885534e-2 7.382780287860479e-2
          </eigenvalues>
        <occupations size="13">
          1.000000000000000e0 1.000000000000000e0 1.000000000000000e0 1.000000000000000e0 1.000000000000000e0
          1.000000000000000e0 1.000000000000000e0 1.000000000000000e0 1.000000000000000e0 1.000000000000000e0
          1.000000000000000e0 1.000000000000000e0 1.000000000000000e0
          </occupations>
      </ks_energies>
      <ks_energies>
        <k_point weight="2.469135802469e-2">1.102218730040575e-1 3.818669496783444e-1 0.000000000000000e0</k_point>
        <npw>4001</npw>
        <eigenvalues size="13">
          -2.133971414858534e0 -1.186701776371951e0 -1.181929344250698e0 -1.179850590133250e0 -3.623308444772115e-1
          -3.446480592524765e-1 -8.460708576339073e-2 -5.078916971748011e-2 -3.682379787056838e-2 -1.127802409850212e-2
          3.549182693267316e-2 5.147167688872116e-2 7.444456019076810e-2
          </eigenvalues>
        <occupations size="13">
          1.000000000000000e0 1.000000000000000e0 1.000000000000000e0 1.000000000000000e0 1.000000000000000e0
          1.000000000000000e0 1.000000000000000e0 1.000000000000000e0 1.000000000000000e0 1.000000000000000e0
          1.000000000000000e0 1.000000000000000e0 1.000000000000000e0
          </occupations>
      </ks_energies>
      <ks_energies>
        <k_point weight="2.469135802469e-2">1.102218730040575e-1 4.455114412914018e-1 0.000000000000000e0</k_point>
        <npw>4009</npw>
        <eigenvalues size="13">
          -2.133804880512287e0 -1.188191662190359e0 -1.181593477442313e0 -1.180367577750968e0 -3.524619955469287e-1
          -3.406114105579143e-1 -9.253378015229496e-2 -6.428361101395420e-2 -3.841950328993366e-2 -1.248813203858381e-2
          3.644674298340952e-2 4.323692897308409e-2 7.965195069872245e-2
          </eigenvalues>
        <occupations size="13">
          1.000000000000000e0 1.000000000000000e0 1.000000000000000e0 1.000000000000000e0 1.000000000000000e0
          1.000000000000000e0 1.000000000000000e0 1.000000000000000e0 1.000000000000000e0 1.000000000000000e0
          1.000000000000000e0 1.000000000000000e0 1.000000000000000e0
          </occupations>
      </ks_energies>
      <ks_energies>
        <k_point weight="2.469135802469e-2">1.102218730040575e-1 5.091559329044592e-1 0.000000000000000e0</k_point>
        <npw>4024</npw>
        <eigenvalues size="13">
          -2.133696122688574e0 -1.189159603691996e0 -1.181373939410383e0 -1.180705010854479e0 -3.455546741924227e-1
          -3.378281587484975e-1 -9.834880422672136e-2 -7.307010396231877e-2 -4.162987177739407e-2 -1.246391098689515e-2
          3.731255088978400e-2 3.846092291837103e-2 8.581779206385638e-2
          </eigenvalues>
        <occupations size="13">
          1.000000000000000e0 1.000000000000000e0 1.000000000000000e0 1.000000000000000e0 1.000000000000000e0
          1.000000000000000e0 1.000000000000000e0 1.000000000000000e0 1.000000000000000e0 1.000000000000000e0
          1.000000000000000e0 1.000000000000000e0 1.000000000000000e0
          </occupations>
      </ks_energies>
      <ks_energies>
        <k_point weight="1.234567901235e-2">1.102218730040575e-1 5.728004245175166e-1 0.000000000000000e0</k_point>
        <npw>4030</npw>
        <eigenvalues size="13">
          -2.133658335347925e0 -1.189494871206663e0 -1.181297361578289e0 -1.180822500067532e0 -3.430547170302492e-1
          -3.368311145119882e-1 -1.004709221496983e-1 -7.611789472384565e-2 -4.316105946531882e-2 -1.228621712569353e-2
          3.513395605559103e-2 3.937120306311534e-2 8.869271264844937e-2
          </eigenvalues>
        <occupations size="13">
          1.000000000000000e0 1.000000000000000e0 1.000000000000000e0 1.000000000000000e0 1.000000000000000e0
          1.000000000000000e0 1.000000000000000e0 1.000000000000000e0 1.000000000000000e0 1.000000000000000e0
          1.000000000000000e0 1.000000000000000e0 1.000000000000000e0
          </occupations>
      </ks_energies>
      <ks_energies>
        <k_point weight="1.234567901235e-2">1.102218730040575e-1 -2.775557561562891e-17 0.000000000000000e0</k_point>
        <npw>3993</npw>
        <eigenvalues size="13">
          -2.134907383309147e0 -1.183814698515111e0 -1.177976046273845e0 -1.177060181354967e0 -4.078611045870819e-1
          -3.636948963135693e-1 -9.598067009417381e-2 -2.488281201599896e-3 1.354450883963819e-2 1.813073433106940e-2
          4.026815685323419e-2 6.298751423431487e-2 1.002950977602415e-1
          </eigenvalues>
        <occupations size="13">
          1.000000000000000e0 1.000000000000000e0 1.000000000000000e0 1.000000000000000e0 1.000000000000000e0
          1.000000000000000e0 1.000000000000000e0 1.000000000000000e0 1.000000000000000e0 1.000000000000000e0
          1.000000000000000e0 1.000000000000000e0 1.000000000000000e0
          </occupations>
      </ks_energies>
      <ks_energies>
        <k_point weight="2.469135802469e-2">1.653328095060863e-1 9.546673741958609e-2 0.000000000000000e0</k_point>
        <npw>4008</npw>
        <eigenvalues size="13">
          -2.134693687686922e0 -1.183385033112707e0 -1.180154415197569e0 -1.177549659047010e0 -3.985312560362809e-1
          -3.597824221213697e-1 -8.652717335358329e-2 -1.928912842829697e-2 -2.199763051726139e-3 2.320946680920567e-2
          2.898682410728666e-2 6.382806679324120e-2 9.254234367376728e-2
          </eigenvalues>
        <occupations size="13">
          1.000000000000000e0 1.000000000000000e0 1.000000000000000e0 1.000000000000000e0 1.000000000000000e0
          1.000000000000000e0 1.000000000000000e0 1.000000000000000e0 1.000000000000000e0 1.000000000000000e0
          1.000000000000000e0 1.000000000000000e0 1.000000000000000e0
          </occupations>
      </ks_energies>
      <ks_energies>
        <k_point weight="2.469135802469e-2">1.653328095060863e-1 1.591112290326435e-1 0.000000000000000e0</k_point>
        <npw>3991</npw>
        <eigenvalues size="13">
          -2.134565408435682e0 -1.183126189764269e0 -1.181373325306329e0 -1.177917711951611e0 -3.926858763848171e-1
          -3.573294954402637e-1 -8.170304993874346e-2 -2.714915931772986e-2 -1.025368940457509e-2 1.783942961765995e-2
          2.829710584747269e-2 6.497937089225191e-2 8.689447787106369e-2
          </eigenvalues>
        <occupations size="13">
          1.000000000000000e0 1.000000000000000e0 1.000000000000000e0 1.000000000000000e0 1.000000000000000e0
          1.000000000000000e0 1.000000000000000e0 1.000000000000000e0 1.000000000000000e0 1.000000000000000e0
          1.000000000000000e0 1.000000000000000e0 1.000000000000000e0
          </occupations>
      </ks_energies>
      <ks_energies>
        <k_point weight="2.469135802469e-2">1.653328095060863e-1 2.227557206457009e-1 0.000000000000000e0</k_point>
        <npw>4007</npw>
        <eigenvalues size="13">
          -2.134392529468923e0 -1.182882804066961e0 -1.182778421907663e0 -1.178541731256489e0 -3.844684160751651e-1
          -3.538687188086679e-1 -7.690878294762037e-2 -3.435576440885680e-2 -1.810211639515641e-2 4.596295992230294e-4
          3.244597582787880e-2 6.689255680437238e-2 7.980538894865842e-2
          </eigenvalues>
        <occupations size="13">
          1.000000000000000e0 1.000000000000000e0 1.000000000000000e0 1.000000000000000e0 1.000000000000000e0
          1.000000000000000e0 1.000000000000000e0 1.000000000000000e0 1.000000000000000e0 1.000000000000000e0
          1.000000000000000e0 1.000000000000000e0 1.000000000000000e0
          </occupations>
      </ks_energies>
      <ks_energies>
        <k_point weight="2.469135802469e-2">1.653328095060863e-1 2.864002122587582e-1 0.000000000000000e0</k_point>
        <npw>4007</npw>
        <eigenvalues size="13">
          -2.134195677312724e0 -1.184497638333222e0 -1.182381608917132e0 -1.179339689888867e0 -3.745693413857894e-1
          -3.496858337121830e-1 -7.593258055979647e-2 -3.675400843100674e-2 -2.978249062181146e-2 -1.250038346825337e-2
          3.179493721639443e-2 6.467233293251359e-2 7.479869078324041e-2
          </eigenvalues>
        <occupations size="13">
          1.000000000000000e0 1.000000000000000e0 1.000000000000000e0 1.000000000000000e0 1.000000000000000e0
          1.000000000000000e0 1.000000000000000e0 1.000000000000000e0 1.000000000000000e0 1.000000000000000e0
          1.000000000000000e0 1.000000000000000e0 1.000000000000000e0
          </occupations>
      </ks_energies>
      <ks_energies>
        <k_point weight="2.469135802469e-2">1.653328095060863e-1 3.500447038718156e-1 0.000000000000000e0</k_point>
        <npw>3995</npw>
        <eigenvalues size="13">
          -2.133998571594403e0 -1.186045962094894e0 -1.181984243613263e0 -1.180190094297132e0 -3.639585286711879e-1
          -3.451950424965044e-1 -7.996728818610888e-2 -4.687061900869182e-2 -3.443842191447449e-2 -1.625711725227059e-2
          2.553552418321441e-2 5.799968018243257e-2 7.484295971333337e-2
          </eigenvalues>
        <occupations size="13">
          1.000000000000000e0 1.000000000000000e0 1.000000000000000e0 1.000000000000000e0 1.000000000000000e0
          1.000000000000000e0 1.000000000000000e0 1.000000000000000e0 1.000000000000000e0 1.000000000000000e0
          1.000000000000000e0 1.000000000000000e0 1.000000000000000e0
          </occupations>
      </ks_energies>
      <ks_energies>
        <k_point weight="2.469135802469e-2">1.653328095060863e-1 4.136891954848730e-1 0.000000000000000e0</k_point>
        <npw>3993</npw>
        <eigenvalues size="13">
          -2.133825082359090e0 -1.187370180078974e0 -1.181634445766224e0 -1.180966005273860e0 -3.539025557957455e-1
          -3.409440169524870e-1 -8.556206175309489e-2 -6.275004513406161e-2 -3.355586966078055e-2 -1.581319711487854e-2
          1.941290304734672e-2 4.899633401897311e-2 7.906384511446275e-2
          </eigenvalues>
        <occupations size="13">
          1.000000000000000e0 1.000000000000000e0 1.000000000000000e0 1.000000000000000e0 1.000000000000000e0
          1.000000000000000e0 1.000000000000000e0 1.000000000000000e0 1.000000000000000e0 1.000000000000000e0
          1.000000000000000e0 1.000000000000000e0 1.000000000000000e0
          </occupations>
      </ks_energies>
      <ks_energies>
        <k_point weight="2.469135802469e-2">1.653328095060863e-1 4.773336870979304e-1 0.000000000000000e0</k_point>
        <npw>4012</npw>
        <eigenvalues size="13">
          -2.133696257345969e0 -1.188336134926536e0 -1.181555297078269e0 -1.181374759459395e0 -3.458996020727012e-1
          -3.375734966443382e-1 -9.003484567034514e-2 -7.448214706784515e-2 -3.688054719244293e-2 -1.352349914373664e-2
          1.728615092495816e-2 4.031792437865852e-2 8.568332453756248e-2
          </eigenvalues>
        <occupations size="13">
          1.000000000000000e0 1.000000000000000e0 1.000000000000000e0 1.000000000000000e0 1.000000000000000e0
          1.000000000000000e0 1.000000000000000e0 1.000000000000000e0 1.000000000000000e0 1.000000000000000e0
          1.000000000000000e0 1.000000000000000e0 1.000000000000000e0
          </occupations>
      </ks_energies>
      <ks_energies>
        <k_point weight="2.469135802469e-2">1.653328095060863e-1 5.409781787109878e-1 0.000000000000000e0</k_point>
        <npw>4016</npw>
        <eigenvalues size="13">
          -2.133627649710576e0 -1.188845053631545e0 -1.181871290845912e0 -1.181236328040880e0 -3.414193489194219e-1
          -3.356946722809628e-1 -9.238200485485230e-2 -8.068927122857385e-2 -4.049750304386043e-2 -1.135843833019408e-2
          1.724023715609818e-2 3.475061497852618e-2 9.125699196447030e-2
          </eigenvalues>
        <occupations size="13">
          1.000000000000000e0 1.000000000000000e0 1.000000000000000e0 1.000000000000000e0 1.000000000000000e0
          1.000000000000000e0 1.000000000000000e0 1.000000000000000e0 1.000000000000000e0 1.000000000000000e0
          1.000000000000000e0 1.000000000000000e0 1.000000000000000e0
          </occupations>
      </ks_energies>
      <ks_energies>
        <k_point weight="2.469135802469e-2">1.653328095060863e-1 -3.182224580652876e-2 0.000000000000000e0</k_point>
        <npw>4000</npw>
        <eigenvalues size="13">
          -2.134761860232201e0 -1.183521902476808e0 -1.179430908784930e0 -1.177425001875758e0 -4.015620031899209e-1
          -3.610507723924550e-1 -8.930658443053568e-2 -1.423773960834454e-2 4.573922914916602e-3 1.987765938514907e-2
          2.966939110746244e-2 6.685915276257437e-2 9.544676055667567e-2
          </eigenvalues>
        <occupations size="13">
          1.000000000000000e0 1.000000000000000e0 1.000000000000000e0 1.000000000000000e0 1.000000000000000e0
          1.000000000000000e0 1.000000000000000e0 1.000000000000000e0 1.000000000000000e0 1.000000000000000e0
          1.000000000000000e0 1.000000000000000e0 1.000000000000000e0
          </occupations>
      </ks_energies>
      <ks_energies>
        <k_point weight="2.469135802469e-2">2.204437460081150e-1 1.272889832261148e-1 0.000000000000000e0</k_point>
        <npw>3990</npw>
        <eigenvalues size="13">
          -2.134477239091577e0 -1.182948355535542e0 -1.182327323891487e0 -1.178049127878912e0 -3.885298366726315e-1
          -3.556066815919627e-1 -7.973125121089798e-2 -3.189774651330795e-2 -1.830737712999579e-2 1.834149166759675e-2
          3.314667649074762e-2 5.848436863272206e-2 8.239165320742831e-2
          </eigenvalues>
        <occupations size="13">
          1.000000000000000e0 1.000000000000000e0 1.000000000000000e0 1.000000000000000e0 1.000000000000000e0
          1.000000000000000e0 1.000000000000000e0 1.000000000000000e0 1.000000000000000e0 1.000000000000000e0
          1.000000000000000e0 1.000000000000000e0 1.000000000000000e0
          </occupations>
      </ks_energies>
      <ks_energies>
        <k_point weight="2.469135802469e-2">2.204437460081150e-1 1.909334748391722e-1 0.000000000000000e0</k_point>
        <npw>4003</npw>
        <eigenvalues size="13">
          -2.134341917221922e0 -1.183566328615012e0 -1.182675979839605e0 -1.178473858756682e0 -3.819501645298593e-1
          -3.528551790033883e-1 -7.776462640989815e-2 -3.638777788448950e-2 -2.603904506717146e-2 7.337806291164894e-3
          3.733143308230441e-2 5.850380472954906e-2 7.687459229284697e-2
          </eigenvalues>
        <occupations size="13">
          1.000000000000000e0 1.000000000000000e0 1.000000000000000e0 1.000000000000000e0 1.000000000000000e0
          1.000000000000000e0 1.000000000000000e0 1.000000000000000e0 1.000000000000000e0 1.000000000000000e0
          1.000000000000000e0 1.000000000000000e0 1.000000000000000e0
          </occupations>
      </ks_energies>
      <ks_energies>
        <k_point weight="2.469135802469e-2">2.204437460081150e-1 2.545779664522296e-1 0.000000000000000e0</k_point>
        <npw>4008</npw>
        <eigenvalues size="13">
          -2.134175742075556e0 -1.184863509632160e0 -1.182341294657349e0 -1.179212493779347e0 -3.734942751236294e-1
          -3.492808404109429e-1 -7.770511558775905e-2 -3.744757513080119e-2 -3.435756466247273e-2 -7.581873265153650e-3
          3.555288295730322e-2 6.014903791972163e-2 7.381832235212792e-2
          </eigenvalues>
        <occupations size="13">
          1.000000000000000e0 1.000000000000000e0 1.000000000000000e0 1.000000000000000e0 1.000000000000000e0
          1.000000000000000e0 1.000000000000000e0 1.000000000000000e0 1.000000000000000e0 1.000000000000000e0
          1.000000000000000e0 1.000000000000000e0 1.000000000000000e0
          </occupations>
      </ks_energies>
      <ks_energies>
        <k_point weight="2.469135802469e-2">2.204437460081150e-1 3.182224580652870e-1 0.000000000000000e0</k_point>
        <npw>3997</npw>
        <eigenvalues size="13">
          -2.133998700299919e0 -1.186047183259505e0 -1.181984503396469e0 -1.180187953878137e0 -3.639602430099483e-1
          -3.451983858202776e-1 -7.996850516350822e-2 -4.687374857744008e-2 -3.444436698352374e-2 -1.624569109846114e-2
          2.554365876242664e-2 5.799946593382378e-2 7.483995758229827e-2
          </eigenvalues>
        <occupations size="13">
          1.000000000000000e0 1.000000000000000e0 1.000000000000000e0 1.000000000000000e0 1.000000000000000e0
          1.000000000000000e0 1.000000000000000e0 1.000000000000000e0 1.000000000000000e0 1.000000000000000e0
          1.000000000000000e0 1.000000000000000e0 1.000000000000000e0
          </occupations>
      </ks_energies>
      <ks_energies>
        <k_point weight="2.469135802469e-2">2.204437460081150e-1 3.818669496783444e-1 0.000000000000000e0</k_point>
        <npw>4007</npw>
        <eigenvalues size="13">
          -2.133832241181874e0 -1.187002062416711e0 -1.181649482830297e0 -1.181259114910760e0 -3.544097012620024e-1
          -3.410523342531327e-1 -8.259356261922740e-2 -6.209585202683283e-2 -3.056781592204473e-2 -1.734414107892698e-2
          1.164424829626229e-2 5.150329305640318e-2 7.864077051873069e-2
          </eigenvalues>
        <occupations size="13">
          1.000000000000000e0 1.000000000000000e0 1.000000000000000e0 1.000000000000000e0 1.000000000000000e0
          1.000000000000000e0 1.000000000000000e0 1.000000000000000e0 1.000000000000000e0 1.000000000000000e0
          1.000000000000000e0 1.000000000000000e0 1.000000000000000e0
          </occupations>
      </ks_energies>
      <ks_energies>
        <k_point weight="2.469135802469e-2">2.204437460081150e-1 4.455114412914018e-1 0.000000000000000e0</k_point>
        <npw>3997</npw>
        <eigenvalues size="13">
          -2.133696378415647e0 -1.187663100281551e0 -1.182245029556605e0 -1.181374881391610e0 -3.461234831769798e-1
          -3.374083319069654e-1 -8.375851830765068e-2 -7.534849033257771e-2 -3.061018875279446e-2 -1.440572857708277e-2
          3.906604602765291e-4 4.264034416740135e-2 8.506364972444979e-2
          </eigenvalues>
        <occupations size="13">
          1.000000000000000e0 1.000000000000000e0 1.000000000000000e0 1.000000000000000e0 1.000000000000000e0
          1.000000000000000e0 1.000000000000000e0 1.000000000000000e0 1.000000000000000e0 1.000000000000000e0
          1.000000000000000e0 1.000000000000000e0 1.000000000000000e0
          </occupations>
      </ks_energies>
      <ks_energies>
        <k_point weight="2.469135802469e-2">2.204437460081150e-1 5.091559329044592e-1 0.000000000000000e0</k_point>
        <npw>4018</npw>
        <eigenvalues size="13">
          -2.133607722601111e0 -1.188031384299103e0 -1.182952256126693e0 -1.181196805508923e0 -3.404342728104258e-1
          -3.348808921254662e-1 -8.411283293107825e-2 -8.320285740230753e-2 -3.587724098458744e-2 -1.015687432582875e-2
          -4.106973800477612e-3 3.443104304481479e-2 9.254294726978330e-2
          </eigenvalues>
        <occupations size="13">
          1.000000000000000e0 1.000000000000000e0 1.000000000000000e0 1.000000000000000e0 1.000000000000000e0
          1.000000000000000e0 1.000000000000000e0 1.000000000000000e0 1.000000000000000e0 1.000000000000000e0
          1.000000000000000e0 1.000000000000000e0 1.000000000000000e0
          </occupations>
      </ks_energies>
      <ks_energies>
        <k_point weight="1.234567901235e-2">2.204437460081150e-1 5.728004245175166e-1 0.000000000000000e0</k_point>
        <npw>4021</npw>
        <eigenvalues size="13">
          -2.133576911052736e0 -1.188145497087975e0 -1.183211106014044e0 -1.181134675367834e0 -3.384009037774537e-1
          -3.339724400954294e-1 -8.716543585439013e-2 -8.253181037695683e-2 -3.918743754165099e-2 -7.952979600170407e-3
          -4.883361862587459e-3 3.083067212944436e-2 9.620172577923762e-2
          </eigenvalues>
        <occupations size="13">
          1.000000000000000e0 1.000000000000000e0 1.000000000000000e0 1.000000000000000e0 1.000000000000000e0
          1.000000000000000e0 1.000000000000000e0 1.000000000000000e0 1.000000000000000e0 1.000000000000000e0
          1.000000000000000e0 1.000000000000000e0 1.000000000000000e0
          </occupations>
      </ks_energies>
      <ks_energies>
        <k_point weight="2.469135802469e-2">2.204437460081150e-1 -6.364449161305735e-2 0.000000000000000e0</k_point>
        <npw>3991</npw>
        <eigenvalues size="13">
          -2.134565531175717e0 -1.183126349856133e0 -1.181374212496652e0 -1.177915752700036e0 -3.926878054658346e-1
          -3.573322283563622e-1 -8.170431594621157e-2 -2.714856602713374e-2 -1.025276147282531e-2 1.784411396181806e-2
          2.830155096141957e-2 6.497780487549131e-2 8.689002591733896e-2
          </eigenvalues>
        <occupations size="13">
          1.000000000000000e0 1.000000000000000e0 1.000000000000000e0 1.000000000000000e0 1.000000000000000e0
          1.000000000000000e0 1.000000000000000e0 1.000000000000000e0 1.000000000000000e0 1.000000000000000e0
          1.000000000000000e0 1.000000000000000e0 1.000000000000000e0
          </occupations>
      </ks_energies>
      <ks_energies>
        <k_point weight="1.234567901235e-2">2.204437460081150e-1 -5.551115123125783e-17 0.000000000000000e0</k_point>
        <npw>4003</npw>
        <eigenvalues size="13">
          -2.134596216150473e0 -1.183188825205260e0 -1.180998155592611e0 -1.177915058341725e0 -3.941082571134702e-1
          -3.579194192623987e-1 -8.247561945263413e-2 -2.513263079483079e-2 -5.620115100012696e-3 1.448480106854846e-2
          2.626273449520424e-2 6.926091044575173e-2 8.855467297756634e-2
          </eigenvalues>
        <occupations size="13">
          1.000000000000000e0 1.000000000000000e0 1.000000000000000e0 1.000000000000000e0 1.000000000000000e0
          1.000000000000000e0 1.000000000000000e0 1.000000000000000e0 1.000000000000000e0 1.000000000000000e0
          1.000000000000000e0 1.000000000000000e0 1.000000000000000e0
          </occupations>
      </ks_energies>
      <ks_energies>
        <k_point weight="2.469135802469e-2">2.755546825101439e-1 1.591112290326435e-1 0.000000000000000e0</k_point>
        <npw>4016</npw>
        <eigenvalues size="13">
          -2.134246706849197e0 -1.184620169951528e0 -1.182483965435637e0 -1.178581250464360e0 -3.771115070277929e-1
          -3.508837358804606e-1 -7.956356102330399e-2 -3.850408960354379e-2 -3.413672786065594e-2 8.343005040708102e-3
          4.382895968713771e-2 5.083266030544193e-2 7.250205109074291e-2
          </eigenvalues>
        <occupations size="13">
          1.000000000000000e0 1.000000000000000e0 1.000000000000000e0 1.000000000000000e0 1.000000000000000e0
          1.000000000000000e0 1.000000000000000e0 1.000000000000000e0 1.000000000000000e0 1.000000000000000e0
          1.000000000000000e0 1.000000000000000e0 1.000000000000000e0
          </occupations>
      </ks_energies>
      <ks_energies>
        <k_point weight="2.469135802469e-2">2.755546825101439e-1 2.227557206457009e-1 0.000000000000000e0</k_point>
        <npw>4007</npw>
        <eigenvalues size="13">
          -2.134118097873318e0 -1.185737834831977e0 -1.182224662473939e0 -1.179028865259578e0 -3.703600567764507e-1
          -3.480781869173777e-1 -8.214146986968135e-2 -4.175676995243930e-2 -3.880468926198740e-2 -7.793048852992854e-4
          4.484994368830564e-2 5.044983769811116e-2 7.100438207682291e-2
          </eigenvalues>
        <occupations size="13">
          1.000000000000000e0 1.000000000000000e0 1.000000000000000e0 1.000000000000000e0 1.000000000000000e0
          1.000000000000000e0 1.000000000000000e0 1.000000000000000e0 1.000000000000000e0 1.000000000000000e0
          1.000000000000000e0 1.000000000000000e0 1.000000000000000e0
          </occupations>
      </ks_energies>
      <ks_energies>
        <k_point weight="2.469135802469e-2">2.755546825101439e-1 2.864002122587583e-1 0.000000000000000e0</k_point>
        <npw>4001</npw>
        <eigenvalues size="13">
          -2.133971769126116e0 -1.186704237559881e0 -1.181929804182164e0 -1.179845043251071e0 -3.623358287638443e-1
          -3.446577413463473e-1 -8.461084663556163e-2 -5.079344542524962e-2 -3.683552337104357e-2 -1.124772814258947e-2
          3.551088276877246e-2 5.146874940905977e-2 7.443608000767687e-2
          </eigenvalues>
        <occupations size="13">
          1.000000000000000e0 1.000000000000000e0 1.000000000000000e0 1.000000000000000e0 1.000000000000000e0
          1.000000000000000e0 1.000000000000000e0 1.000000000000000e0 1.000000000000000e0 1.000000000000000e0
          1.000000000000000e0 1.000000000000000e0 1.000000000000000e0
          </occupations>
      </ks_energies>
      <ks_energies>
        <k_point weight="2.469135802469e-2">2.755546825101439e-1 3.500447038718156e-1 0.000000000000000e0</k_point>
        <npw>3993</npw>
        <eigenvalues size="13">
          -2.133825336481467e0 -1.187371998103735e0 -1.181634775826953e0 -1.180961988619029e0 -3.539062048835215e-1
          -3.409513534195509e-1 -8.556637932795873e-2 -6.274788234193636e-2 -3.356316107612311e-2 -1.579687457454330e-2
          1.942807167719672e-2 4.899334898866930e-2 7.905805713050009e-2
          </eigenvalues>
        <occupations size="13">
          1.000000000000000e0 1.000000000000000e0 1.000000000000000e0 1.000000000000000e0 1.000000000000000e0
          1.000000000000000e0 1.000000000000000e0 1.000000000000000e0 1.000000000000000e0 1.000000000000000e0
          1.000000000000000e0 1.000000000000000e0 1.000000000000000e0
          </occupations>
      </ks_energies>
      <ks_energies>
        <k_point weight="2.469135802469e-2">2.755546825101439e-1 4.136891954848730e-1 0.000000000000000e0</k_point>
        <npw>3997</npw>
        <eigenvalues size="13">
          -2.133696509458790e0 -1.187664120595757e0 -1.182242885546423e0 -1.181375051889282e0 -3.461254628227001e-1
          -3.374123144507695e-1 -8.376136526370372e-2 -7.534534254396620e-2 -3.061455529701902e-2 -1.439880717437676e-2
          4.008686837205289e-4 4.263769288160274e-2 8.505991229017217e-2
          </eigenvalues>
        <occupations size="13">
          1.000000000000000e0 1.000000000000000e0 1.000000000000000e0 1.000000000000000e0 1.000000000000000e0
          1.000000000000000e0 1.000000000000000e0 1.000000000000000e0 1.000000000000000e0 1.000000000000000e0
          1.000000000000000e0 1.000000000000000e0 1.000000000000000e0
          </occupations>
      </ks_energies>
      <ks_energies>
        <k_point weight="2.469135802469e-2">2.755546825101439e-1 4.773336870979304e-1 0.000000000000000e0</k_point>
        <npw>4015</npw>
        <eigenvalues size="13">
          -2.133600882528287e0 -1.187592814368105e0 -1.183483694628516e0 -1.181183120079208e0 -3.401094042079204e-1
          -3.345867841786878e-1 -8.537176456879305e-2 -7.875209797195653e-2 -3.064265700537560e-2 -1.640439626228553e-2
          -9.639835435788168e-3 3.433043823562659e-2 9.295958823156736e-2
          </eigenvalues>
        <occupations size="13">
          1.000000000000000e0 1.000000000000000e0 1.000000000000000e0 1.000000000000000e0 1.000000000000000e0
          1.000000000000000e0 1.000000000000000e0 1.000000000000000e0 1.000000000000000e0 1.000000000000000e0
          1.000000000000000e0 1.000000000000000e0 1.000000000000000e0
          </occupations>
      </ks_energies>
      <ks_energies>
        <k_point weight="2.469135802469e-2">2.755546825101439e-1 5.409781787109878e-1 0.000000000000000e0</k_point>
        <npw>4025</npw>
        <eigenvalues size="13">
          -2.133549986647865e0 -1.187342652930868e0 -1.184356468274112e0 -1.181080859251661e0 -3.368198988155941e-1
          -3.330047499403990e-1 -9.084115940482974e-2 -7.246935476770916e-2 -3.800335401586962e-2 -2.204097927458731e-2
          -4.835733478588415e-3 2.760025263385221e-2 9.971945926195957e-2
          </eigenvalues>
        <occupations size="13">
          1.000000000000000e0 1.000000000000000e0 1.000000000000000e0 1.000000000000000e0 1.000000000000000e0
          1.000000000000000e0 1.000000000000000e0 1.000000000000000e0 1.000000000000000e0 1.000000000000000e0
          1.000000000000000e0 1.000000000000000e0 1.000000000000000e0
          </occupations>
      </ks_energies>
      <ks_energies>
        <k_point weight="2.469135802469e-2">2.755546825101439e-1 -9.546673741958609e-2 0.000000000000000e0</k_point>
        <npw>4003</npw>
        <eigenvalues size="13">
          -2.134342047913844e0 -1.183566297126500e0 -1.182676150621898e0 -1.178472769714092e0 -3.819524283735324e-1
          -3.528582496932353e-1 -7.776482795357287e-2 -3.638326040381118e-2 -2.603321892536544e-2 7.337193916298892e-3
          3.732787807629837e-2 5.850265287012610e-2 7.687458634178695e-2
          </eigenvalues>
        <occupations size="13">
          1.000000000000000e0 1.000000000000000e0 1.000000000000000e0 1.000000000000000e0 1.000000000000000e0
          1.000000000000000e0 1.000000000000000e0 1.000000000000000e0 1.000000000000000e0 1.000000000000000e0
          1.000000000000000e0 1.000000000000000e0 1.000000000000000e0
          </occupations>
      </ks_energies>
      <ks_energies>
        <k_point weight="2.469135802469e-2">2.755546825101439e-1 -3.182224580652865e-2 0.000000000000000e0</k_point>
        <npw>4007</npw>
        <eigenvalues size="13">
          -2.134392782898201e0 -1.182883701453018e0 -1.182778753086909e0 -1.178538642528511e0 -3.844725706403239e-1
          -3.538746301895156e-1 -7.690999863776755e-2 -3.435135665312161e-2 -1.809630823089756e-2 4.647383435644848e-4
          3.244631629560515e-2 6.689114436580034e-2 7.980105023164597e-2
          </eigenvalues>
        <occupations size="13">
          1.000000000000000e0 1.000000000000000e0 1.000000000000000e0 1.000000000000000e0 1.000000000000000e0
          1.000000000000000e0 1.000000000000000e0 1.000000000000000e0 1.000000000000000e0 1.000000000000000e0
          1.000000000000000e0 1.000000000000000e0 1.000000000000000e0
          </occupations>
      </ks_energies>
      <ks_energies>
        <k_point weight="2.469135802469e-2">3.306656190121726e-1 1.909334748391722e-1 0.000000000000000e0</k_point>
        <npw>4006</npw>
        <eigenvalues size="13">
          -2.134029671401300e0 -1.186752397272414e0 -1.182046272718736e0 -1.179078287874626e0 -3.654538319166949e-1
          -3.461390886512494e-1 -8.730282434185170e-2 -4.869267086576147e-2 -3.969620358994408e-2 -1.183171197856874e-4
          4.377316384203723e-2 5.377288940181697e-2 6.816159364847079e-2
          </eigenvalues>
        <occupations size="13">
          1.000000000000000e0 1.000000000000000e0 1.000000000000000e0 1.000000000000000e0 1.000000000000000e0
          1.000000000000000e0 1.000000000000000e0 1.000000000000000e0 1.000000000000000e0 1.000000000000000e0
          1.000000000000000e0 1.000000000000000e0 1.000000000000000e0
          </occupations>
      </ks_energies>
      <ks_energies>
        <k_point weight="2.469135802469e-2">3.306656190121726e-1 2.545779664522296e-1 0.000000000000000e0</k_point>
        <npw>4016</npw>
        <eigenvalues size="13">
          -2.133921047988315e0 -1.187631143398301e0 -1.181827515293747e0 -1.179515513072690e0 -3.592616582002679e-1
          -3.435835616388860e-1 -9.127151812531393e-2 -5.569744507024843e-2 -3.954984050126783e-2 -6.501824737202279e-3
          4.318481370874588e-2 5.017693497671920e-2 7.282448956033624e-2
          </eigenvalues>
        <occupations size="13">
          1.000000000000000e0 1.000000000000000e0 1.000000000000000e0 1.000000000000000e0 1.000000000000000e0
          1.000000000000000e0 1.000000000000000e0 1.000000000000000e0 1.000000000000000e0 1.000000000000000e0
          1.000000000000000e0 1.000000000000000e0 1.000000000000000e0
          </occupations>
      </ks_energies>
      <ks_energies>
        <k_point weight="2.469135802469e-2">3.306656190121726e-1 3.182224580652870e-1 0.000000000000000e0</k_point>
        <npw>4009</npw>
        <eigenvalues size="13">
          -2.133805358171721e0 -1.188193991610464e0 -1.181594097345963e0 -1.180361121729642e0 -3.524689599679463e-1
          -3.406252538336681e-1 -9.254126875059745e-2 -6.427887401760106e-2 -3.842598928107704e-2 -1.245516852531023e-2
          3.646820949075695e-2 4.322817247971682e-2 7.964151958991444e-2
          </eigenvalues>
        <occupations size="13">
          1.000000000000000e0 1.000000000000000e0 1.000000000000000e0 1.000000000000000e0 1.000000000000000e0
          1.000000000000000e0 1.000000000000000e0 1.000000000000000e0 1.000000000000000e0 1.000000000000000e0
          1.000000000000000e0 1.000000000000000e0 1.000000000000000e0
          </occupations>
      </ks_energies>
      <ks_energies>
        <k_point weight="2.469135802469e-2">3.306656190121726e-1 3.818669496783444e-1 0.000000000000000e0</k_point>
        <npw>4012</npw>
        <eigenvalues size="13">
          -2.133696634841030e0 -1.188338160491669e0 -1.181550030601145e0 -1.181375250368502e0 -3.459053256281972e-1
          -3.375849307949454e-1 -9.004212750153208e-2 -7.447359631951642e-2 -3.688433184007243e-2 -1.350192541925989e-2
          1.730584482490034e-2 4.030928799791533e-2 8.567338287341475e-2
          </eigenvalues>
        <occupations size="13">
          1.000000000000000e0 1.000000000000000e0 1.000000000000000e0 1.000000000000000e0 1.000000000000000e0
          1.000000000000000e0 1.000000000000000e0 1.000000000000000e0 1.000000000000000e0 1.000000000000000e0
          1.000000000000000e0 1.000000000000000e0 1.000000000000000e0
          </occupations>
      </ks_energies>
      <ks_energies>
        <k_point weight="2.469135802469e-2">3.306656190121726e-1 4.455114412914018e-1 0.000000000000000e0</k_point>
        <npw>4016</npw>
        <eigenvalues size="13">
          -2.133607971349726e0 -1.188032949342581e0 -1.182948409036752e0 -1.181196990803421e0 -3.404384184682161e-1
          -3.348888752840674e-1 -8.410463194785827e-2 -8.320784689275582e-2 -3.588054140198147e-2 -1.014319555074982e-2
          -4.091637425232156e-3 3.442280199584603e-2 9.253635922330236e-2
          </eigenvalues>
        <occupations size="13">
          1.000000000000000e0 1.000000000000000e0 1.000000000000000e0 1.000000000000000e0 1.000000000000000e0
          1.000000000000000e0 1.000000000000000e0 1.000000000000000e0 1.000000000000000e0 1.000000000000000e0
          1.000000000000000e0 1.000000000000000e0 1.000000000000000e0
          </occupations>
      </ks_energies>
      <ks_energies>
        <k_point weight="2.469135802469e-2">3.306656190121726e-1 5.091559329044592e-1 0.000000000000000e0</k_point>
        <npw>4025</npw>
        <eigenvalues size="13">
          -2.133550109867437e0 -1.187343820620225e0 -1.184354261270021e0 -1.181081020415280e0 -3.368221114080457e-1
          -3.330087136794738e-1 -9.083644821028507e-2 -7.247053809131153e-2 -3.800683292469346e-2 -2.203293200651705e-2
          -4.828406040782504e-3 2.759442251182320e-2 9.971818082379968e-2
          </eigenvalues>
        <occupations size="13">
          1.000000000000000e0 1.000000000000000e0 1.000000000000000e0 1.000000000000000e0 1.000000000000000e0
          1.000000000000000e0 1.000000000000000e0 1.000000000000000e0 1.000000000000000e0 1.000000000000000e0
          1.000000000000000e0 1.000000000000000e0 1.000000000000000e0
          </occupations>
      </ks_energies>
      <ks_energies>
        <k_point weight="1.234567901235e-2">3.306656190121726e-1 5.728004245175164e-1 0.000000000000000e0</k_point>
        <npw>4035</npw>
        <eigenvalues size="13">
          -2.133530031365653e0 -1.186744940447771e0 -1.185203285440852e0 -1.181040939245381e0 -3.355587140685734e-1
          -3.323312770442252e-1 -9.323671397773264e-2 -6.383159076133933e-2 -4.471856378837758e-2 -2.727542543653880e-2
          -1.806613446922763e-3 2.405455258566867e-2 1.032185721847141e-1
          </eigenvalues>
        <occupations size="13">
          1.000000000000000e0 1.000000000000000e0 1.000000000000000e0 1.000000000000000e0 1.000000000000000e0
          1.000000000000000e0 1.000000000000000e0 1.000000000000000e0 1.000000000000000e0 1.000000000000000e0
          1.000000000000000e0 1.000000000000000e0 1.000000000000000e0
          </occupations>
      </ks_energies>
      <ks_energies>
        <k_point weight="2.469135802469e-2">3.306656190121726e-1 -1.272889832261148e-1 0.000000000000000e0</k_point>
        <npw>4007</npw>
        <eigenvalues size="13">
          -2.134118220894490e0 -1.185737343216068e0 -1.182224823757249e0 -1.179028317810580e0 -3.703624461317089e-1
          -3.480812496278207e-1 -8.213860125944612e-2 -4.174981898982761e-2 -3.880156561034506e-2 -7.806268117639238e-4
          4.484020771172056e-2 5.044788720552261e-2 7.101101190528047e-2
          </eigenvalues>
        <occupations size="13">
          1.000000000000000e0 1.000000000000000e0 1.000000000000000e0 1.000000000000000e0 1.000000000000000e0
          1.000000000000000e0 1.000000000000000e0 1.000000000000000e0 1.000000000000000e0 1.000000000000000e0
          1.000000000000000e0 1.000000000000000e0 1.000000000000000e0
          </occupations>
      </ks_energies>
      <ks_energies>
        <k_point weight="2.469135802469e-2">3.306656190121726e-1 -6.364449161305741e-2 0.000000000000000e0</k_point>
        <npw>4008</npw>
        <eigenvalues size="13">
          -2.134175995905376e0 -1.184863120924745e0 -1.182341626669574e0 -1.179210720752581e0 -3.734988910350372e-1
          -3.492870993356922e-1 -7.770190255483524e-2 -3.744083035570437e-2 -3.434366270579239e-2 -7.584645661875040e-3
          3.553969384444767e-2 6.014668247925005e-2 7.382497242865879e-2
          </eigenvalues>
        <occupations size="13">
          1.000000000000000e0 1.000000000000000e0 1.000000000000000e0 1.000000000000000e0 1.000000000000000e0
          1.000000000000000e0 1.000000000000000e0 1.000000000000000e0 1.000000000000000e0 1.000000000000000e0
          1.000000000000000e0 1.000000000000000e0 1.000000000000000e0
          </occupations>
      </ks_energies>
      <ks_energies>
        <k_point weight="1.234567901235e-2">3.306656190121726e-1 2.775557561562891e-17 0.000000000000000e0</k_point>
        <npw>4007</npw>
        <eigenvalues size="13">
          -2.134196054073508e0 -1.184498285775523e0 -1.182382100431904e0 -1.179335807158532e0 -3.745757711908069e-1
          -3.496951480365866e-1 -7.592974335489573e-2 -3.675003209561811e-2 -2.977024518415266e-2 -1.249477405921273e-2
          3.178629435293576e-2 6.467047198645419e-2 7.480201040434481e-2
          </eigenvalues>
        <occupations size="13">
          1.000000000000000e0 1.000000000000000e0 1.000000000000000e0 1.000000000000000e0 1.000000000000000e0
          1.000000000000000e0 1.000000000000000e0 1.000000000000000e0 1.000000000000000e0 1.000000000000000e0
          1.000000000000000e0 1.000000000000000e0 1.000000000000000e0
          </occupations>
      </ks_energies>
      <ks_energies>
        <k_point weight="2.469135802469e-2">3.857765555142014e-1 2.227557206457009e-1 0.000000000000000e0</k_point>
        <npw>4032</npw>
        <eigenvalues size="13">
          -2.133852633630056e0 -1.188478547468562e0 -1.181689407287841e0 -1.179484010541051e0 -3.550881462173282e-1
          -3.420136034999500e-1 -9.700172597788907e-2 -6.059114100450910e-2 -4.140896872386835e-2 -6.486454472726400e-3
          3.860670561456087e-2 6.158804567380836e-2 7.112159400733981e-2
          </eigenvalues>
        <occupations size="13">
          1.000000000000000e0 1.000000000000000e0 1.000000000000000e0 1.000000000000000e0 1.000000000000000e0
          1.000000000000000e0 1.000000000000000e0 1.000000000000000e0 1.000000000000000e0 1.000000000000000e0
          1.000000000000000e0 1.000000000000000e0 1.000000000000000e0
          </occupations>
      </ks_energies>
      <ks_energies>
        <k_point weight="2.469135802469e-2">3.857765555142014e-1 2.864002122587583e-1 0.000000000000000e0</k_point>
        <npw>4024</npw>
        <eigenvalues size="13">
          -2.133774653047794e0 -1.189027287827805e0 -1.181532060618101e0 -1.179875521050356e0 -3.503193690550863e-1
          -3.400400297145633e-1 -9.975766656598985e-2 -6.613315536721371e-2 -4.207001006706246e-2 -1.011596104185995e-2
          3.794659707591918e-2 5.484430372749466e-2 7.875398409742149e-2
          </eigenvalues>
        <occupations size="13">
          1.000000000000000e0 1.000000000000000e0 1.000000000000000e0 1.000000000000000e0 1.000000000000000e0
          1.000000000000000e0 1.000000000000000e0 1.000000000000000e0 1.000000000000000e0 1.000000000000000e0
          1.000000000000000e0 1.000000000000000e0 1.000000000000000e0
          </occupations>
      </ks_energies>
      <ks_energies>
        <k_point weight="2.469135802469e-2">3.857765555142014e-1 3.500447038718157e-1 0.000000000000000e0</k_point>
        <npw>4024</npw>
        <eigenvalues size="13">
          -2.133696701017545e0 -1.189161619081852e0 -1.181374691199210e0 -1.180698030847392e0 -3.455634989814344e-1
          -3.378455997643364e-1 -9.835818691555023e-2 -7.305827724202953e-2 -4.163112138964743e-2 -1.242683294686042e-2
          3.729686618484323e-2 3.848511443237199e-2 8.580440959754727e-2
          </eigenvalues>
        <occupations size="13">
          1.000000000000000e0 1.000000000000000e0 1.000000000000000e0 1.000000000000000e0 1.000000000000000e0
          1.000000000000000e0 1.000000000000000e0 1.000000000000000e0 1.000000000000000e0 1.000000000000000e0
          1.000000000000000e0 1.000000000000000e0 1.000000000000000e0
          </occupations>
      </ks_energies>
      <ks_energies>
        <k_point weight="2.469135802469e-2">3.857765555142014e-1 4.136891954848730e-1 0.000000000000000e0</k_point>
        <npw>4016</npw>
        <eigenvalues size="13">
          -2.133628127758518e0 -1.188846894887327e0 -1.181865372503027e0 -1.181236950725861e0 -3.414270894300707e-1
          -3.357095141004893e-1 -9.238921992395323e-2 -8.067524569253198e-2 -4.049814749316149e-2 -1.133141612054220e-2
          1.726062658353145e-2 3.473543505478793e-2 9.124674021060221e-2
          </eigenvalues>
        <occupations size="13">
          1.000000000000000e0 1.000000000000000e0 1.000000000000000e0 1.000000000000000e0 1.000000000000000e0
          1.000000000000000e0 1.000000000000000e0 1.000000000000000e0 1.000000000000000e0 1.000000000000000e0
          1.000000000000000e0 1.000000000000000e0 1.000000000000000e0
          </occupations>
      </ks_energies>
      <ks_energies>
        <k_point weight="2.469135802469e-2">3.857765555142014e-1 4.773336870979304e-1 0.000000000000000e0</k_point>
        <npw>4021</npw>
        <eigenvalues size="13">
          -2.133577266014387e0 -1.188147107955853e0 -1.183206490891608e0 -1.181135138683627e0 -3.384071813613167e-1
          -3.339836858942790e-1 -8.715254071275659e-2 -8.253395234532192e-2 -3.919018158254938e-2 -7.933978720565683e-3
          -4.869358133420501e-3 3.081681934716018e-2 9.619867600406007e-2
          </eigenvalues>
        <occupations size="13">
          1.000000000000000e0 1.000000000000000e0 1.000000000000000e0 1.000000000000000e0 1.000000000000000e0
          1.000000000000000e0 1.000000000000000e0 1.000000000000000e0 1.000000000000000e0 1.000000000000000e0
          1.000000000000000e0 1.000000000000000e0 1.000000000000000e0
          </occupations>
      </ks_energies>
      <ks_energies>
        <k_point weight="2.469135802469e-2">3.857765555142014e-1 5.409781787109878e-1 0.000000000000000e0</k_point>
        <npw>4025</npw>
        <eigenvalues size="13">
          -2.133550210459729e0 -1.187343769330020e0 -1.184353473897266e0 -1.181081151930074e0 -3.368242821376000e-1
          -3.330118877502701e-1 -9.083188438956579e-2 -7.246357107575041e-2 -3.801152510629948e-2 -2.203376561099066e-2
          -4.824233404704711e-3 2.759019077743042e-2 9.972413368675628e-2
          </eigenvalues>
        <occupations size="13">
          1.000000000000000e0 1.000000000000000e0 1.000000000000000e0 1.000000000000000e0 1.000000000000000e0
          1.000000000000000e0 1.000000000000000e0 1.000000000000000e0 1.000000000000000e0 1.000000000000000e0
          1.000000000000000e0 1.000000000000000e0 1.000000000000000e0
          </occupations>
      </ks_energies>
      <ks_energies>
        <k_point weight="2.469135802469e-2">3.857765555142014e-1 -1.591112290326435e-1 0.000000000000000e0</k_point>
        <npw>4016</npw>
        <eigenvalues size="13">
          -2.133921148462800e0 -1.187630541090712e0 -1.181827647096324e0 -1.179515276905174e0 -3.592638583183064e-1
          -3.435862067167209e-1 -9.126685734840699e-2 -5.569153453320761e-2 -3.954938861475309e-2 -6.502158975626710e-3
          4.318215224158540e-2 5.016631772664802e-2 7.283496769959754e-2
          </eigenvalues>
        <occupations size="13">
          1.000000000000000e0 1.000000000000000e0 1.000000000000000e0 1.000000000000000e0 1.000000000000000e0
          1.000000000000000e0 1.000000000000000e0 1.000000000000000e0 1.000000000000000e0 1.000000000000000e0
          1.000000000000000e0 1.000000000000000e0 1.000000000000000e0
          </occupations>
      </ks_energies>
      <ks_energies>
        <k_point weight="2.469135802469e-2">3.857765555142014e-1 -9.546673741958609e-2 0.000000000000000e0</k_point>
        <npw>4001</npw>
        <eigenvalues size="13">
          -2.133971992689929e0 -1.186703241476394e0 -1.181930096890386e0 -1.179844161202631e0 -3.623403922068402e-1
          -3.446635815480463e-1 -8.460274468893466e-2 -5.078043448995819e-2 -3.683226571451459e-2 -1.124959662496074e-2
          3.549391179103100e-2 5.146498471861904e-2 7.444977315961304e-2
          </eigenvalues>
        <occupations size="13">
          1.000000000000000e0 1.000000000000000e0 1.000000000000000e0 1.000000000000000e0 1.000000000000000e0
          1.000000000000000e0 1.000000000000000e0 1.000000000000000e0 1.000000000000000e0 1.000000000000000e0
          1.000000000000000e0 1.000000000000000e0 1.000000000000000e0
          </occupations>
      </ks_energies>
      <ks_energies>
        <k_point weight="2.469135802469e-2">3.857765555142014e-1 -3.182224580652868e-2 0.000000000000000e0</k_point>
        <npw>3997</npw>
        <eigenvalues size="13">
          -2.133999054846578e0 -1.186046538680767e0 -1.181984966243284e0 -1.180185594886975e0 -3.639669655122386e-1
          -3.452076592493794e-1 -7.995940123789751e-2 -4.685540004069421e-2 -3.443908123346466e-2 -1.624646009248241e-2
          2.552356145907266e-2 5.799568568437676e-2 7.485434500483303e-2
          </eigenvalues>
        <occupations size="13">
          1.000000000000000e0 1.000000000000000e0 1.000000000000000e0 1.000000000000000e0 1.000000000000000e0
          1.000000000000000e0 1.000000000000000e0 1.000000000000000e0 1.000000000000000e0 1.000000000000000e0
          1.000000000000000e0 1.000000000000000e0 1.000000000000000e0
          </occupations>
      </ks_energies>
      <ks_energies>
        <k_point weight="2.469135802469e-2">4.408874920162301e-1 2.545779664522296e-1 0.000000000000000e0</k_point>
        <npw>4038</npw>
        <eigenvalues size="13">
          -2.133736945424313e0 -1.189598078243749e0 -1.181456174186236e0 -1.179747128373843e0 -3.477900847265026e-1
          -3.391772165053285e-1 -1.043241339495414e-1 -6.842646791804613e-2 -4.405398313070494e-2 -1.042539709049972e-2
          3.558563577375789e-2 6.642190029098827e-2 7.715472141846464e-2
          </eigenvalues>
        <occupations size="13">
          1.000000000000000e0 1.000000000000000e0 1.000000000000000e0 1.000000000000000e0 1.000000000000000e0
          1.000000000000000e0 1.000000000000000e0 1.000000000000000e0 1.000000000000000e0 1.000000000000000e0
          1.000000000000000e0 1.000000000000000e0 1.000000000000000e0
          </occupations>
      </ks_energies>
      <ks_energies>
        <k_point weight="2.469135802469e-2">4.408874920162301e-1 3.182224580652870e-1 0.000000000000000e0</k_point>
        <npw>4027</npw>
        <eigenvalues size="13">
          -2.133696714264749e0 -1.189766668303296e0 -1.181374761898399e0 -1.180066559458461e0 -3.452591644742570e-1
          -3.380732142078895e-1 -1.047101000924767e-1 -7.172047783707080e-2 -4.437495266182482e-2 -1.186192583117174e-2
          3.524648003543779e-2 5.777950007269538e-2 8.366860882738735e-2
          </eigenvalues>
        <occupations size="13">
          1.000000000000000e0 1.000000000000000e0 1.000000000000000e0 1.000000000000000e0 1.000000000000000e0
          1.000000000000000e0 1.000000000000000e0 1.000000000000000e0 1.000000000000000e0 1.000000000000000e0
          1.000000000000000e0 1.000000000000000e0 1.000000000000000e0
          </occupations>
      </ks_energies>
      <ks_energies>
        <k_point weight="2.469135802469e-2">4.408874920162301e-1 3.818669496783444e-1 0.000000000000000e0</k_point>
        <npw>4032</npw>
        <eigenvalues size="13">
          -2.133658984659313e0 -1.189496761754531e0 -1.181298206683504e0 -1.180815356908391e0 -3.430650175031614e-1
          -3.368507735575125e-1 -1.004788793810678e-1 -7.610186630340220e-2 -4.316090595816383e-2 -1.224658554737983e-2
          3.511394307415652e-2 3.939457954910994e-2 8.868198454568475e-2
          </eigenvalues>
        <occupations size="13">
          1.000000000000000e0 1.000000000000000e0 1.000000000000000e0 1.000000000000000e0 1.000000000000000e0
          1.000000000000000e0 1.000000000000000e0 1.000000000000000e0 1.000000000000000e0 1.000000000000000e0
          1.000000000000000e0 1.000000000000000e0 1.000000000000000e0
          </occupations>
      </ks_energies>
      <ks_energies>
        <k_point weight="2.469135802469e-2">4.408874920162301e-1 4.455114412914018e-1 0.000000000000000e0</k_point>
        <npw>4016</npw>
        <eigenvalues size="13">
          -2.133628193393209e0 -1.188846469803891e0 -1.181865256502337e0 -1.181237036789372e0 -3.414286953624947e-1
          -3.357114633548250e-1 -9.238458260140810e-2 -8.067178280265761e-2 -4.049942084883670e-2 -1.133035864084451e-2
          1.725673877892976e-2 3.473331632348325e-2 9.125381978722727e-2
          </eigenvalues>
        <occupations size="13">
          1.000000000000000e0 1.000000000000000e0 1.000000000000000e0 1.000000000000000e0 1.000000000000000e0
          1.000000000000000e0 1.000000000000000e0 1.000000000000000e0 1.000000000000000e0 1.000000000000000e0
          1.000000000000000e0 1.000000000000000e0 1.000000000000000e0
          </occupations>
      </ks_energies>
      <ks_energies>
        <k_point weight="2.469135802469e-2">4.408874920162301e-1 5.091559329044592e-1 0.000000000000000e0</k_point>
        <npw>4018</npw>
        <eigenvalues size="13">
          -2.133608143245996e0 -1.188032293226720e0 -1.182947800252659e0 -1.181197354152130e0 -3.404422056946300e-1
          -3.348939369525020e-1 -8.409658453742990e-2 -8.319709898962458e-2 -3.588280428535951e-2 -1.013951675889187e-2
          -4.099666815451900e-3 3.441783937783274e-2 9.254923886374383e-2
          </eigenvalues>
        <occupations size="13">
          1.000000000000000e0 1.000000000000000e0 1.000000000000000e0 1.000000000000000e0 1.000000000000000e0
          1.000000000000000e0 1.000000000000000e0 1.000000000000000e0 1.000000000000000e0 1.000000000000000e0
          1.000000000000000e0 1.000000000000000e0 1.000000000000000e0
          </occupations>
      </ks_energies>
      <ks_energies>
        <k_point weight="1.234567901235e-2">4.408874920162301e-1 5.728004245175166e-1 0.000000000000000e0</k_point>
        <npw>4015</npw>
        <eigenvalues size="13">
          -2.133601172014364e0 -1.187592675656710e0 -1.183481412931294e0 -1.181183498202170e0 -3.401154276621918e-1
          -3.345957132363117e-1 -8.535901706331948e-2 -7.873957600683454e-2 -3.064639855085801e-2 -1.640989074233119e-2
          -9.630862773078537e-3 3.432175150435517e-2 9.297256037508504e-2
          </eigenvalues>
        <occupations size="13">
          1.000000000000000e0 1.000000000000000e0 1.000000000000000e0 1.000000000000000e0 1.000000000000000e0
          1.000000000000000e0 1.000000000000000e0 1.000000000000000e0 1.000000000000000e0 1.000000000000000e0
          1.000000000000000e0 1.000000000000000e0 1.000000000000000e0
          </occupations>
      </ks_energies>
      <ks_energies>
        <k_point weight="2.469135802469e-2">4.408874920162301e-1 -1.909334748391721e-1 0.000000000000000e0</k_point>
        <npw>4026</npw>
        <eigenvalues size="13">
          -2.133774724000866e0 -1.189027068006892e0 -1.181532150458365e0 -1.179875456108711e0 -3.503209726694059e-1
          -3.400418414782693e-1 -9.975366975424262e-2 -6.612929971508784e-2 -4.207081732926296e-2 -1.011557896060775e-2
          3.794421357589171e-2 5.483668864012344e-2 7.876384762574556e-2
          </eigenvalues>
        <occupations size="13">
          1.000000000000000e0 1.000000000000000e0 1.000000000000000e0 1.000000000000000e0 1.000000000000000e0
          1.000000000000000e0 1.000000000000000e0 1.000000000000000e0 1.000000000000000e0 1.000000000000000e0
          1.000000000000000e0 1.000000000000000e0 1.000000000000000e0
          </occupations>
      </ks_energies>
      <ks_energies>
        <k_point weight="2.469135802469e-2">4.408874920162301e-1 -1.272889832261148e-1 0.000000000000000e0</k_point>
        <npw>4007</npw>
        <eigenvalues size="13">
          -2.133805518998629e0 -1.188192891025349e0 -1.181594303935252e0 -1.180360587531256e0 -3.524727385102884e-1
          -3.406298257846739e-1 -9.253220979202423e-2 -6.426932417710317e-2 -3.842645216329736e-2 -1.245504113497972e-2
          3.645541532897866e-2 4.322389330516094e-2 7.965678818182980e-2
          </eigenvalues>
        <occupations size="13">
          1.000000000000000e0 1.000000000000000e0 1.000000000000000e0 1.000000000000000e0 1.000000000000000e0
          1.000000000000000e0 1.000000000000000e0 1.000000000000000e0 1.000000000000000e0 1.000000000000000e0
          1.000000000000000e0 1.000000000000000e0 1.000000000000000e0
          </occupations>
      </ks_energies>
      <ks_energies>
        <k_point weight="2.469135802469e-2">4.408874920162301e-1 -6.364449161305741e-2 0.000000000000000e0</k_point>
        <npw>3993</npw>
        <eigenvalues size="13">
          -2.133825625820772e0 -1.187370772516986e0 -1.181635154406345e0 -1.180960792464576e0 -3.539123186409117e-1
          -3.409593523750333e-1 -8.555357229380290e-2 -6.273251911387158e-2 -3.356080650354546e-2 -1.579630818918389e-2
          1.940881321531187e-2 4.898820435891331e-2 7.907632662707902e-2
          </eigenvalues>
        <occupations size="13">
          1.000000000000000e0 1.000000000000000e0 1.000000000000000e0 1.000000000000000e0 1.000000000000000e0
          1.000000000000000e0 1.000000000000000e0 1.000000000000000e0 1.000000000000000e0 1.000000000000000e0
          1.000000000000000e0 1.000000000000000e0 1.000000000000000e0
          </occupations>
      </ks_energies>
      <ks_energies>
        <k_point weight="1.234567901235e-2">4.408874920162301e-1 0.000000000000000e0 0.000000000000000e0</k_point>
        <npw>4007</npw>
        <eigenvalues size="13">
          -2.133832661534679e0 -1.187001528697064e0 -1.181650031871779e0 -1.181256102135850e0 -3.544178867076994e-1
          -3.410640590836647e-1 -8.258074512349424e-2 -6.207727669474679e-2 -3.056533656232495e-2 -1.733876431576598e-2
          1.162590679198257e-2 5.149735098483684e-2 7.865826674255626e-2
          </eigenvalues>
        <occupations size="13">
          1.000000000000000e0 1.000000000000000e0 1.000000000000000e0 1.000000000000000e0 1.000000000000000e0
          1.000000000000000e0 1.000000000000000e0 1.000000000000000e0 1.000000000000000e0 1.000000000000000e0
          1.000000000000000e0 1.000000000000000e0 1.000000000000000e0
          </occupations>
      </ks_energies>
      <ks_energies>
        <k_point weight="1.234567901235e-2">-4.959984285182589e-1 -2.864002122587583e-1 0.000000000000000e0</k_point>
        <npw>4034</npw>
        <eigenvalues size="13">
          -2.133696734189992e0 -1.189985149168869e0 -1.181374772198330e0 -1.179838376893622e0 -3.451380920451514e-1
          -3.381628079565748e-1 -1.070269712359697e-1 -7.116487975799145e-2 -4.528571606743356e-2 -1.175740204144231e-2
          3.460375775735932e-2 6.803243027884848e-2 8.009198262268793e-2
          </eigenvalues>
        <occupations size="13">
          1.000000000000000e0 1.000000000000000e0 1.000000000000000e0 1.000000000000000e0 1.000000000000000e0
          1.000000000000000e0 1.000000000000000e0 1.000000000000000e0 1.000000000000000e0 1.000000000000000e0
          1.000000000000000e0 1.000000000000000e0 1.000000000000000e0
          </occupations>
      </ks_energies>
      <ks_energies>
        <k_point weight="2.469135802469e-2">-4.959984285182589e-1 -2.227557206457009e-1 0.000000000000000e0</k_point>
        <npw>4027</npw>
        <eigenvalues size="13">
          -2.133696737126033e0 -1.189766496468930e0 -1.181374791719070e0 -1.180066542263349e0 -3.452597552403895e-1
          -3.380738592922047e-1 -1.047085449947924e-1 -7.171914111496152e-2 -4.437541662238943e-2 -1.186166244744086e-2
          3.524552255681414e-2 5.777669425563113e-2 8.367286615157509e-2
          </eigenvalues>
        <occupations size="13">
          1.000000000000000e0 1.000000000000000e0 1.000000000000000e0 1.000000000000000e0 1.000000000000000e0
          1.000000000000000e0 1.000000000000000e0 1.000000000000000e0 1.000000000000000e0 1.000000000000000e0
          1.000000000000000e0 1.000000000000000e0 1.000000000000000e0
          </occupations>
      </ks_energies>
      <ks_energies>
        <k_point weight="2.469135802469e-2">-4.959984285182589e-1 -1.591112290326435e-1 0.000000000000000e0</k_point>
        <npw>4024</npw>
        <eigenvalues size="13">
          -2.133696789512892e0 -1.189161000108000e0 -1.181374807109525e0 -1.180697919356931e0 -3.455656913435068e-1
          -3.378481257262727e-1 -9.835233302400416e-2 -7.305327906954695e-2 -4.163256612507180e-2 -1.242602051561626e-2
          3.729387854404082e-2 3.847842334234829e-2 8.581519733116851e-2
          </eigenvalues>
        <occupations size="13">
          1.000000000000000e0 1.000000000000000e0 1.000000000000000e0 1.000000000000000e0 1.000000000000000e0
          1.000000000000000e0 1.000000000000000e0 1.000000000000000e0 1.000000000000000e0 1.000000000000000e0
          1.000000000000000e0 1.000000000000000e0 1.000000000000000e0
          </occupations>
      </ks_energies>
      <ks_energies>
        <k_point weight="2.469135802469e-2">-4.959984285182589e-1 -9.546673741958610e-2 0.000000000000000e0</k_point>
        <npw>4012</npw>
        <eigenvalues size="13">
          -2.133696823844486e0 -1.188337073661036e0 -1.181549549876323e0 -1.181375497678068e0 -3.459097048730659e-1
          -3.375903979809735e-1 -9.003071555439483e-2 -7.446360539152673e-2 -3.688573821836679e-2 -1.350012296574919e-2
          1.729390113434645e-2 4.030442959249452e-2 8.568982888529277e-2
          </eigenvalues>
        <occupations size="13">
          1.000000000000000e0 1.000000000000000e0 1.000000000000000e0 1.000000000000000e0 1.000000000000000e0
          1.000000000000000e0 1.000000000000000e0 1.000000000000000e0 1.000000000000000e0 1.000000000000000e0
          1.000000000000000e0 1.000000000000000e0 1.000000000000000e0
          </occupations>
      </ks_energies>
      <ks_energies>
        <k_point weight="2.469135802469e-2">-4.959984285182589e-1 -3.182224580652870e-2 0.000000000000000e0</k_point>
        <npw>3997</npw>
        <eigenvalues size="13">
          -2.133696821773138e0 -1.187663136595299e0 -1.182241259333205e0 -1.181375459399778e0 -3.461321223281818e-1
          -3.374214667957581e-1 -8.374670468987071e-2 -7.533050950811586e-2 -3.061301412522717e-2 -1.439405287228170e-2
          3.842211354217735e-4 4.263106143032009e-2 8.507806142890459e-2
          </eigenvalues>
        <occupations size="13">
          1.000000000000000e0 1.000000000000000e0 1.000000000000000e0 1.000000000000000e0 1.000000000000000e0
          1.000000000000000e0 1.000000000000000e0 1.000000000000000e0 1.000000000000000e0 1.000000000000000e0
          1.000000000000000e0 1.000000000000000e0 1.000000000000000e0
          </occupations>
      </ks_energies>
    </band_structure>
    <forces rank="2" dims="3 3" order="F">
      0.000000000000000e0 2.873573479214642e-5 0.000000000000000e0
      2.504152123578323e-29 -1.436786739607322e-5 -3.614768385415260e-5
      -2.504152123578323e-29 -1.436786739607321e-5 3.614768385415260e-5
      </forces>
    <stress rank="2" dims="3 3" order="F">
      -1.125174432303928e-6 0.000000000000000e0 0.000000000000000e0
      0.000000000000000e0 -8.219056883826054e-7 0.000000000000000e0
      0.000000000000000e0 -1.547103201928670e-35 -2.904594351609350e-6
      </stress>
  </output>
  <status>0</status>
  <timing_info>
    <total label="PWSCF">
      <cpu>8.351596200000001e1</cpu>
      <wall>8.725461912155152e1</wall>
    </total>
    <partial label="electrons" calls="1">
      <cpu>7.998043700000001e1</cpu>
      <wall>8.350338196754455e1</wall>
    </partial>
  </timing_info>
  <closed DATE="15 Nov 2021" TIME="15:42:21"></closed>
</qes:espresso>
